{"dates":[{"date":"dez 7, 2017","hasGoal":false,"hasRevenue":false,"sessionCount":1,"sessions":[{"duration":"12:47","deviceCategory":"mobile","channel":"Referral","activitySummary":{"PAGEVIEW":"4"},"activities":[{"time":"6:43 PM","type":"PAGEVIEW","repeatActivityTimes":[],"details":[{"Título da página":["Book in Xisto"],"URL da página":["/pt/lodge-catalog/index?LodgeSearch[type_id]=&LodgeSearch[fulltext]=&LodgeSearch[date_start]=2017-12-07&LodgeSearch[date_end]=2017-12-12&LodgeSearch[num_adults]=2&LodgeSearch[num_children]=0"]}],"pageTitle":"Book in Xisto"},{"time":"6:43 PM","type":"PAGEVIEW","repeatActivityTimes":[],"details":[{"Título da página":["Book in Xisto"],"URL da página":["/pt"]}],"pageTitle":"Book in Xisto"},{"time":"6:43 PM","type":"PAGEVIEW","repeatActivityTimes":[],"details":[{"Título da página":["Integrity constraint violation (#23000)"],"URL da página":["/pt/lodge-catalog/index?LodgeSearch[type_id]=&LodgeSearch[fulltext]=&LodgeSearch[date_start]=2018-1-26&LodgeSearch[date_end]=2018-1-28&LodgeSearch[num_adults]=3&LodgeSearch[num_children]=0"]}],"pageTitle":"Integrity constraint violation (#23000)"},{"time":"6:30 PM","type":"PAGEVIEW","repeatActivityTimes":[],"details":[{"Título da página":["Book in Xisto"],"URL da página":["/pt"]}],"pageTitle":"Book in Xisto"}]}]}]}